blackduck_c_cpp/__init__.py
blackduck_c_cpp/run_build_capture.py
blackduck_c_cpp/bdba/__init__.py
blackduck_c_cpp/bdba/upload_bdba.py
blackduck_c_cpp/bdio/__init__.py
blackduck_c_cpp/bdio/bdio2_python_transformer.py
blackduck_c_cpp/coverity_json/__init__.py
blackduck_c_cpp/coverity_json/cov_json_parse.py
blackduck_c_cpp/katiska/__init__.py
blackduck_c_cpp/katiska/custom_types.py
blackduck_c_cpp/katiska/version_king.py
blackduck_c_cpp/katiska/bdio/__init__.py
blackduck_c_cpp/katiska/bdio/bdio_entries.py
blackduck_c_cpp/katiska/bdio/bdio_paths.py
blackduck_c_cpp/pkg_manager/__init__.py
blackduck_c_cpp/pkg_manager/ld_debug_parse.py
blackduck_c_cpp/pkg_manager/pkg_manager_bom.py
blackduck_c_cpp/pkg_manager/pkg_manager_detector.py
blackduck_c_cpp/sig_scanner/__init__.py
blackduck_c_cpp/sig_scanner/emit_wrapper.py
blackduck_c_cpp/sig_scanner/run_sig_scanner.py
blackduck_c_cpp/util/__init__.py
blackduck_c_cpp/util/build_log_parser.py
blackduck_c_cpp/util/c_arg_parser.py
blackduck_c_cpp/util/cov_install.py
blackduck_c_cpp/util/global_settings.py
blackduck_c_cpp/util/hub_api.py
blackduck_c_cpp/util/util.py
blackduck_c_cpp/util/zip_file.py
blackduck_c_cpp-3.0.5.dist-info/LICENSE
blackduck_c_cpp-3.0.5.dist-info/METADATA
blackduck_c_cpp-3.0.5.dist-info/WHEEL
blackduck_c_cpp-3.0.5.dist-info/entry_points.txt
blackduck_c_cpp-3.0.5.dist-info/top_level.txt
blackduck_c_cpp-3.0.5.dist-info/RECORD
