Metadata-Version: 2.1
Name: blackduck-c-cpp
Version: 3.0.5
Summary: Scanning for c/c++ projects using blackduck and coverity tools
Classifier: Programming Language :: Python :: 3
Classifier: License :: Other/Proprietary License
Requires-Python: >=3.7
License-File: LICENSE
Requires-Dist: requests>=2.28.2
Requires-Dist: numpy>=1.24.2
Requires-Dist: python-dateutil>=2.8.1
Requires-Dist: pytz>=2021.1
Requires-Dist: six>=1.15.0
Requires-Dist: tqdm>=4.58.0
Requires-Dist: blackduck>=1.1.0
Requires-Dist: configargparse>=1.4
Requires-Dist: structlog>=20.1.0
Requires-Dist: pyyaml>=5.4.1
Requires-Dist: pandas>=1.1.5
Requires-Dist: urllib3<1.27,>=1.26.15
Requires-Dist: chardet<5,>=4.0.0
Requires-Dist: requests-toolbelt>=0.9.0
Requires-Dist: google-cloud-storage>=2.6.0
Requires-Dist: certifi>=2023.07.22
